{
  "ticker": "OKE",
  "dimension": "ARQ",
  "calendardate": "1997-03-31 00:00:00",
  "datekey": "1997-03-31 00:00:00",
  "reportperiod": "1997-02-28 00:00:00",
  "fiscalperiod": "1997-Q2",
  "lastupdated": "2025-04-30 00:00:00",
  "accoci": 0,
  "assets": 1333414000,
  "assetsavg": null,
  "assetsc": 317550000,
  "assetsnc": 1015864000,
  "assetturnover": null,
  "bvps": 4.315,
  "capex": NaN,
  "cashneq": 6095000,
  "cashnequsd": 6095000,
  "cor": 350053000,
  "consolinc": 38241000,
  "currentratio": 1.232,
  "de": 1.822,
  "debt": 396195000,
  "debtc": 53977000,
  "debtnc": 342218000,
  "debtusd": 396195000,
  "deferredrev": 0,
  "depamor": NaN,
  "deposits": 0,
  "divyield": 0.046,
  "dps": 0.075,
  "ebit": 71057000,
  "ebitda": NaN,
  "ebitdamargin": NaN,
  "ebitdausd": NaN,
  "ebitusd": 71057000,
  "ebt": 62059000,
  "eps": 0.347,
  "epsdil": NaN,
  "epsusd": 0.347,
  "equity": 472580000,
  "equityavg": null,
  "equityusd": 472580000,
  "ev": 1113310358,
  "evebit": NaN,
  "evebitda": NaN,
  "fcf": NaN,
  "fcfps": NaN,
  "fxusd": 1.0,
  "gp": 123600000,
  "grossmargin": 0.261,
  "intangibles": 0,
  "intexp": 8998000,
  "invcap": 1465679000,
  "invcapavg": null,
  "inventory": 50932000,
  "investments": 0,
  "investmentsc": 0,
  "investmentsnc": 0,
  "liabilities": 860834000,
  "liabilitiesc": 257835000,
  "liabilitiesnc": 602999000,
  "marketcap": 723210358,
  "ncf": NaN,
  "ncfbus": NaN,
  "ncfcommon": NaN,
  "ncfdebt": NaN,
  "ncfdiv": NaN,
  "ncff": NaN,
  "ncfi": NaN,
  "ncfinv": NaN,
  "ncfo": NaN,
  "ncfx": NaN,
  "netinc": 38241000,
  "netinccmn": 38134000,
  "netinccmnusd": 38134000,
  "netincdis": 0,
  "netincnci": 0,
  "netmargin": 0.081,
  "opex": 52543000,
  "opinc": 71057000,
  "payables": 146481000,
  "payoutratio": 0.216,
  "pb": 1.53,
  "pe": NaN,
  "pe1": NaN,
  "ppnenet": 824980000,
  "prefdivis": 107000,
  "price": 6.5,
  "ps": NaN,
  "ps1": NaN,
  "receivables": 232948000,
  "retearn": 241402000,
  "revenue": 473653000,
  "revenueusd": 473653000,
  "rnd": 0,
  "roa": null,
  "roe": null,
  "roic": null,
  "ros": null,
  "sbcomp": NaN,
  "sgna": 0,
  "sharefactor": 1.0,
  "sharesbas": 111263132,
  "shareswa": 109512000,
  "shareswadil": NaN,
  "sps": 4.325,
  "tangibles": 1333414000,
  "taxassets": 0,
  "taxexp": 23818000,
  "taxliabilities": 202625000,
  "tbvps": 12.176,
  "workingcapital": 59715000
}