{
  "ticker": "XOM",
  "dimension": "ARQ",
  "calendardate": "1993-12-31 00:00:00",
  "datekey": "1994-03-11 00:00:00",
  "reportperiod": "1993-12-31 00:00:00",
  "fiscalperiod": "1993-Q4",
  "lastupdated": "2025-05-05 00:00:00",
  "accoci": -370000000,
  "assets": 84145000000,
  "assetsavg": null,
  "assetsc": 14859000000,
  "assetsnc": 69286000000,
  "assetturnover": null,
  "bvps": 7.002,
  "capex": NaN,
  "cashneq": 983000000,
  "cashnequsd": 983000000,
  "cor": NaN,
  "consolinc": NaN,
  "currentratio": 0.799,
  "de": 1.419,
  "debt": 12615000000,
  "debtc": 4109000000,
  "debtnc": 8506000000,
  "debtusd": 12615000000,
  "deferredrev": 770000000,
  "depamor": NaN,
  "deposits": 0,
  "divyield": 0.044,
  "dps": 0.18,
  "ebit": NaN,
  "ebitda": NaN,
  "ebitdamargin": NaN,
  "ebitdausd": NaN,
  "ebitusd": NaN,
  "ebt": NaN,
  "eps": NaN,
  "epsdil": NaN,
  "epsusd": NaN,
  "equity": 34792000000,
  "equityavg": null,
  "equityusd": 34792000000,
  "ev": 92681319516,
  "evebit": 11.0,
  "evebitda": 6.806,
  "fcf": NaN,
  "fcfps": NaN,
  "fxusd": 1.0,
  "gp": NaN,
  "grossmargin": NaN,
  "intangibles": 0,
  "intexp": NaN,
  "invcap": 77187000000,
  "invcapavg": null,
  "inventory": 5472000000,
  "investments": 5459000000,
  "investmentsc": 669000000,
  "investmentsnc": 4790000000,
  "liabilities": 49353000000,
  "liabilitiesc": 18590000000,
  "liabilitiesnc": 30763000000,
  "marketcap": 81049319516,
  "ncf": NaN,
  "ncfbus": NaN,
  "ncfcommon": NaN,
  "ncfdebt": NaN,
  "ncfdiv": NaN,
  "ncff": NaN,
  "ncfi": NaN,
  "ncfinv": NaN,
  "ncfo": NaN,
  "ncfx": NaN,
  "netinc": NaN,
  "netinccmn": NaN,
  "netinccmnusd": NaN,
  "netincdis": NaN,
  "netincnci": NaN,
  "netmargin": NaN,
  "opex": NaN,
  "opinc": NaN,
  "payables": 12122000000,
  "payoutratio": NaN,
  "pb": 2.33,
  "pe": 15.35,
  "pe1": 15.506,
  "ppnenet": 61962000000,
  "prefdivis": NaN,
  "price": 16.312,
  "ps": 0.729,
  "ps1": 0.729,
  "receivables": 6860000000,
  "retearn": 49365000000,
  "revenue": NaN,
  "revenueusd": NaN,
  "rnd": NaN,
  "roa": null,
  "roe": null,
  "roic": null,
  "ros": null,
  "sbcomp": NaN,
  "sgna": NaN,
  "sharefactor": 1.0,
  "sharesbas": 4968540660,
  "shareswa": 4968540660,
  "shareswadil": NaN,
  "sps": NaN,
  "tangibles": 84145000000,
  "taxassets": 0,
  "taxexp": NaN,
  "taxliabilities": 13298000000,
  "tbvps": 16.936,
  "workingcapital": -3731000000
}