{
  "ticker": "MRK",
  "dimension": "ARQ",
  "calendardate": "1996-12-31 00:00:00",
  "datekey": "1997-03-19 00:00:00",
  "reportperiod": "1996-12-31 00:00:00",
  "fiscalperiod": "1996-Q4",
  "lastupdated": "2025-05-02 00:00:00",
  "accoci": 0,
  "assets": 24293100000,
  "assetsavg": null,
  "assetsc": 7726600000,
  "assetsnc": 16566500000,
  "assetturnover": null,
  "bvps": 4.947,
  "capex": NaN,
  "cashneq": 1352400000,
  "cashnequsd": 1352400000,
  "cor": NaN,
  "consolinc": NaN,
  "currentratio": 1.6,
  "de": 1.029,
  "debt": 1762000000,
  "debtc": 606100000,
  "debtnc": 1155900000,
  "debtusd": 1762000000,
  "deferredrev": 0,
  "depamor": NaN,
  "deposits": 0,
  "divyield": 0.017,
  "dps": 0.21,
  "ebit": NaN,
  "ebitda": NaN,
  "ebitdamargin": NaN,
  "ebitdausd": NaN,
  "ebitusd": NaN,
  "ebt": NaN,
  "eps": NaN,
  "epsdil": NaN,
  "epsusd": NaN,
  "equity": 11970500000,
  "equityavg": null,
  "equityusd": 11970500000,
  "ev": 111123888222,
  "evebit": 20.0,
  "evebitda": 17.335,
  "fcf": NaN,
  "fcfps": NaN,
  "fxusd": 1.0,
  "gp": NaN,
  "grossmargin": NaN,
  "intangibles": 6736600000,
  "intexp": NaN,
  "invcap": 13136900000,
  "invcapavg": null,
  "inventory": 2148800000,
  "investments": 3328600000,
  "investmentsc": 829200000,
  "investmentsnc": 2499400000,
  "liabilities": 12322600000,
  "liabilitiesc": 4829200000,
  "liabilitiesnc": 7493400000,
  "marketcap": 110714288222,
  "ncf": NaN,
  "ncfbus": NaN,
  "ncfcommon": NaN,
  "ncfdebt": NaN,
  "ncfdiv": NaN,
  "ncff": NaN,
  "ncfi": NaN,
  "ncfinv": NaN,
  "ncfo": NaN,
  "ncfx": NaN,
  "netinc": NaN,
  "netinccmn": NaN,
  "netinccmnusd": NaN,
  "netincdis": NaN,
  "netincnci": NaN,
  "netmargin": NaN,
  "opex": NaN,
  "opinc": NaN,
  "payables": 2937800000,
  "payoutratio": NaN,
  "pb": 9.249,
  "pe": 28.525,
  "pe1": 28.594,
  "ppnenet": 5926700000,
  "prefdivis": NaN,
  "price": 45.75,
  "ps": 5.584,
  "ps1": 5.584,
  "receivables": 2655900000,
  "retearn": 14817700000,
  "revenue": NaN,
  "revenueusd": NaN,
  "rnd": NaN,
  "roa": null,
  "roe": null,
  "roic": null,
  "ros": null,
  "sbcomp": NaN,
  "sgna": NaN,
  "sharefactor": 1.0,
  "sharesbas": 2419984442,
  "shareswa": 2419984442,
  "shareswadil": NaN,
  "sps": NaN,
  "tangibles": 17556500000,
  "taxassets": 0,
  "taxexp": NaN,
  "taxliabilities": 4829900000,
  "tbvps": 7.255,
  "workingcapital": 2897400000
}