{
  "ticker": "LVS",
  "dimension": "ARQ",
  "calendardate": "2003-12-31 00:00:00",
  "datekey": "2004-12-08 00:00:00",
  "reportperiod": "2003-12-31 00:00:00",
  "fiscalperiod": "2003-Q4",
  "lastupdated": "2025-07-25 00:00:00",
  "accoci": 0,
  "assets": 1917035000,
  "assetsavg": null,
  "assetsc": 272739000,
  "assetsnc": 1644296000,
  "assetturnover": null,
  "bvps": 0.499,
  "capex": NaN,
  "cashneq": 294592000,
  "cashnequsd": 294592000,
  "cor": NaN,
  "consolinc": NaN,
  "currentratio": 1.221,
  "de": 10.826,
  "debt": 1566495000,
  "debtc": 41379000,
  "debtnc": 1525116000,
  "debtusd": 1566495000,
  "deferredrev": 0,
  "depamor": NaN,
  "deposits": 0,
  "divyield": NaN,
  "dps": 0.0,
  "ebit": NaN,
  "ebitda": NaN,
  "ebitdamargin": NaN,
  "ebitdausd": NaN,
  "ebitusd": NaN,
  "ebt": NaN,
  "eps": NaN,
  "epsdil": NaN,
  "epsusd": NaN,
  "equity": 162108000,
  "equityavg": null,
  "equityusd": 162108000,
  "ev": NaN,
  "evebit": NaN,
  "evebitda": NaN,
  "fcf": NaN,
  "fcfps": NaN,
  "fxusd": 1.0,
  "gp": NaN,
  "grossmargin": NaN,
  "intangibles": 0,
  "intexp": NaN,
  "invcap": 2965572000,
  "invcapavg": null,
  "inventory": 6251000,
  "investments": 0,
  "investmentsc": 0,
  "investmentsnc": 0,
  "liabilities": 1754927000,
  "liabilitiesc": 223366000,
  "liabilitiesnc": 1531561000,
  "marketcap": NaN,
  "ncf": NaN,
  "ncfbus": NaN,
  "ncfcommon": NaN,
  "ncfdebt": NaN,
  "ncfdiv": NaN,
  "ncff": NaN,
  "ncfi": NaN,
  "ncfinv": NaN,
  "ncfo": NaN,
  "ncfx": NaN,
  "netinc": NaN,
  "netinccmn": NaN,
  "netinccmnusd": NaN,
  "netincdis": NaN,
  "netincnci": NaN,
  "netmargin": NaN,
  "opex": NaN,
  "opinc": NaN,
  "payables": 23911000,
  "payoutratio": NaN,
  "pb": NaN,
  "pe": NaN,
  "pe1": NaN,
  "ppnenet": 1484670000,
  "prefdivis": NaN,
  "price": NaN,
  "ps": NaN,
  "ps1": NaN,
  "receivables": 52084000,
  "retearn": 8289000,
  "revenue": NaN,
  "revenueusd": NaN,
  "rnd": NaN,
  "roa": null,
  "roe": null,
  "roic": null,
  "ros": null,
  "sbcomp": NaN,
  "sgna": NaN,
  "sharefactor": 1.0,
  "sharesbas": 350589263,
  "shareswa": 324618420,
  "shareswadil": NaN,
  "sps": NaN,
  "tangibles": 1917035000,
  "taxassets": 0,
  "taxexp": NaN,
  "taxliabilities": 0,
  "tbvps": 5.906,
  "workingcapital": 49373000
}