{
  "ticker": "LMT",
  "dimension": "ARQ",
  "calendardate": "1993-12-31 00:00:00",
  "datekey": "1994-03-07 00:00:00",
  "reportperiod": "1993-12-31 00:00:00",
  "fiscalperiod": "1993-Q4",
  "lastupdated": "2025-07-22 00:00:00",
  "accoci": 0,
  "assets": 8961000000,
  "assetsavg": null,
  "assetsc": 3840000000,
  "assetsnc": 5121000000,
  "assetturnover": null,
  "bvps": 19.42,
  "capex": NaN,
  "cashneq": 147000000,
  "cashnequsd": 147000000,
  "cor": NaN,
  "consolinc": NaN,
  "currentratio": 1.516,
  "de": 2.668,
  "debt": 2596000000,
  "debtc": 49000000,
  "debtnc": 2547000000,
  "debtusd": 2596000000,
  "deferredrev": 606000000,
  "depamor": NaN,
  "deposits": 0,
  "divyield": 0.02,
  "dps": 0.163,
  "ebit": NaN,
  "ebitda": NaN,
  "ebitdamargin": NaN,
  "ebitdausd": NaN,
  "ebitusd": NaN,
  "ebt": NaN,
  "eps": NaN,
  "epsdil": NaN,
  "epsusd": NaN,
  "equity": 2443000000,
  "equityavg": null,
  "equityusd": 2443000000,
  "ev": 6588692260,
  "evebit": 8.0,
  "evebitda": 4.91,
  "fcf": NaN,
  "fcfps": NaN,
  "fxusd": 1.0,
  "gp": NaN,
  "grossmargin": NaN,
  "intangibles": 2207000000,
  "intexp": NaN,
  "invcap": 6670000000,
  "invcapavg": null,
  "inventory": 1699000000,
  "investments": 0,
  "investmentsc": 0,
  "investmentsnc": 0,
  "liabilities": 6518000000,
  "liabilitiesc": 2533000000,
  "liabilitiesnc": 3985000000,
  "marketcap": 4139692260,
  "ncf": NaN,
  "ncfbus": NaN,
  "ncfcommon": NaN,
  "ncfdebt": NaN,
  "ncfdiv": NaN,
  "ncff": NaN,
  "ncfi": NaN,
  "ncfinv": NaN,
  "ncfo": NaN,
  "ncfx": NaN,
  "netinc": NaN,
  "netinccmn": NaN,
  "netinccmnusd": NaN,
  "netincdis": NaN,
  "netincnci": NaN,
  "netmargin": NaN,
  "opex": NaN,
  "opinc": NaN,
  "payables": 841000000,
  "payoutratio": NaN,
  "pb": 1.695,
  "pe": 9.81,
  "pe1": 9.851,
  "ppnenet": 1950000000,
  "prefdivis": NaN,
  "price": 33.0,
  "ps": 0.317,
  "ps1": 0.318,
  "receivables": 1644000000,
  "retearn": 2427000000,
  "revenue": NaN,
  "revenueusd": NaN,
  "rnd": NaN,
  "roa": null,
  "roe": null,
  "roic": null,
  "ros": null,
  "sbcomp": NaN,
  "sgna": NaN,
  "sharefactor": 1.0,
  "sharesbas": 125445220,
  "shareswa": 125800000,
  "shareswadil": NaN,
  "sps": NaN,
  "tangibles": 6754000000,
  "taxassets": 33000000,
  "taxexp": NaN,
  "taxliabilities": 44000000,
  "tbvps": 53.688,
  "workingcapital": 1307000000
}